my_package/__init__.py
my_project_require-0.1.0.dist-info/licenses/LICENSE
my_project_require-0.1.0.dist-info/METADATA
my_project_require-0.1.0.dist-info/WHEEL
my_project_require-0.1.0.dist-info/top_level.txt
my_project_require-0.1.0.dist-info/RECORD
